hvcc/__init__.py
hvcc/compiler.py
hvcc/core/__init__.py
hvcc/core/hv2ir/BufferPool.py
hvcc/core/hv2ir/Connection.py
hvcc/core/hv2ir/HIrConvolution.py
hvcc/core/hv2ir/HIrInlet.py
hvcc/core/hv2ir/HIrLorenz.py
hvcc/core/hv2ir/HIrOutlet.py
hvcc/core/hv2ir/HIrPack.py
hvcc/core/hv2ir/HIrReceive.py
hvcc/core/hv2ir/HIrSend.py
hvcc/core/hv2ir/HIrSwitchcase.py
hvcc/core/hv2ir/HIrTabhead.py
hvcc/core/hv2ir/HIrTabread.py
hvcc/core/hv2ir/HIrTabwrite.py
hvcc/core/hv2ir/HLangAdc.py
hvcc/core/hv2ir/HLangBinop.py
hvcc/core/hv2ir/HLangBiquad.py
hvcc/core/hv2ir/HLangDac.py
hvcc/core/hv2ir/HLangDelay.py
hvcc/core/hv2ir/HLangIf.py
hvcc/core/hv2ir/HLangLine.py
hvcc/core/hv2ir/HLangMessage.py
hvcc/core/hv2ir/HLangNoise.py
hvcc/core/hv2ir/HLangPhasor.py
hvcc/core/hv2ir/HLangPrint.py
hvcc/core/hv2ir/HLangRandom.py
hvcc/core/hv2ir/HLangReceive.py
hvcc/core/hv2ir/HLangSend.py
hvcc/core/hv2ir/HLangSequence.py
hvcc/core/hv2ir/HLangSlice.py
hvcc/core/hv2ir/HLangSystem.py
hvcc/core/hv2ir/HLangTable.py
hvcc/core/hv2ir/HLangUnop.py
hvcc/core/hv2ir/HLangVar.py
hvcc/core/hv2ir/HLangVario.py
hvcc/core/hv2ir/HeavyException.py
hvcc/core/hv2ir/HeavyGraph.py
hvcc/core/hv2ir/HeavyIrObject.py
hvcc/core/hv2ir/HeavyLangObject.py
hvcc/core/hv2ir/HeavyParser.py
hvcc/core/hv2ir/LocalVars.py
hvcc/core/hv2ir/__init__.py
hvcc/core/hv2ir/hv2ir.py
hvcc/core/json/heavy.ir.json
hvcc/core/json/heavy.lang.json
hvcc/generators/__init__.py
hvcc/generators/c2daisy/__init__.py
hvcc/generators/c2daisy/c2daisy.py
hvcc/generators/c2daisy/json2daisy/LICENSE.md
hvcc/generators/c2daisy/json2daisy/__init__.py
hvcc/generators/c2daisy/json2daisy/json2daisy.py
hvcc/generators/c2daisy/json2daisy/resources/LICENSE
hvcc/generators/c2daisy/json2daisy/resources/component_defs.json
hvcc/generators/c2daisy/json2daisy/resources/component_defs_patchsm.json
hvcc/generators/c2daisy/json2daisy/resources/component_defs_petalsm.json
hvcc/generators/c2daisy/json2daisy/resources/field.json
hvcc/generators/c2daisy/json2daisy/resources/patch.json
hvcc-0.14.0.dist-info/LICENSE
hvcc-0.14.0.dist-info/METADATA
hvcc-0.14.0.dist-info/WHEEL
hvcc-0.14.0.dist-info/entry_points.txt
hvcc-0.14.0.dist-info/RECORD
