Metadata-Version: 2.3
Name: hvcc
Version: 0.14.0
Summary: `hvcc` is a python-based dataflow audio programming language compiler that generates C/C++ code and a variety of specific framework wrappers.
License: GPLv3
Author: Enzien Audio, Wasted Audio
Requires-Python: >=3.9,<4.0
Classifier: Development Status :: 4 - Beta
Classifier: Intended Audience :: Developers
Classifier: License :: OSI Approved :: GNU General Public License v3 (GPLv3)
Classifier: License :: Other/Proprietary License
Classifier: Programming Language :: Python :: 3
Classifier: Programming Language :: Python :: 3.9
Classifier: Programming Language :: Python :: 3.10
Classifier: Programming Language :: Python :: 3.11
Classifier: Programming Language :: Python :: 3.12
Classifier: Programming Language :: Python :: 3.13
Classifier: Topic :: Software Development :: Compilers
Requires-Dist: Jinja2 (>=2.11)
Requires-Dist: pydantic (>=2.9.1)
Project-URL: Documentation, https://wasted-audio.github.io/hvcc/
Project-URL: Repository, https://github.com/Wasted-Audio/hvcc
